{"nodes": [{"id": "simulate_testing_script", "label": "simulate_testing.R", "file_type": "code", "source_file": "testing/simulate_testing.R", "source_location": null, "source_url": null, "captured_at": null, "author": null, "contributor": null}, {"id": "scenario_sc1_bmi20pct_af_mrtl", "label": "Scenario sc1: 20% BMI reduction + 20% AF mortality reduction", "file_type": "code", "source_file": "testing/simulate_testing.R", "source_location": null, "source_url": null, "captured_at": null, "author": null, "contributor": null}, {"id": "exposure_prb_af_mrtl", "label": "prb_af_mrtl1/prb_af_mrtl2 (AF mortality probabilities)", "file_type": "code", "source_file": "testing/simulate_testing.R", "source_location": null, "source_url": null, "captured_at": null, "author": null, "contributor": null}], "edges": [{"source": "simulate_testing_script", "target": "global_r", "relation": "sources", "confidence": "EXTRACTED", "confidence_score": 1.0, "source_file": "testing/simulate_testing.R", "source_location": null, "weight": 1.0}, {"source": "simulate_testing_script", "target": "simulation_class_new", "relation": "calls", "confidence": "EXTRACTED", "confidence_score": 1.0, "source_file": "testing/simulate_testing.R", "source_location": null, "weight": 1.0}, {"source": "simulate_testing_script", "target": "simulation_run", "relation": "calls", "confidence": "EXTRACTED", "confidence_score": 1.0, "source_file": "testing/simulate_testing.R", "source_location": null, "weight": 1.0}, {"source": "simulate_testing_script", "target": "simulation_del_logs", "relation": "calls", "confidence": "EXTRACTED", "confidence_score": 1.0, "source_file": "testing/simulate_testing.R", "source_location": null, "weight": 1.0}, {"source": "simulate_testing_script", "target": "simulation_del_outputs", "relation": "calls", "confidence": "EXTRACTED", "confidence_score": 1.0, "source_file": "testing/simulate_testing.R", "source_location": null, "weight": 1.0}, {"source": "simulate_testing_script", "target": "simulation_update_primary_prevention_scn", "relation": "calls", "confidence": "EXTRACTED", "confidence_score": 1.0, "source_file": "testing/simulate_testing.R", "source_location": null, "weight": 1.0}, {"source": "simulate_testing_script", "target": "simulation_update_secondary_prevention_scn", "relation": "calls", "confidence": "EXTRACTED", "confidence_score": 1.0, "source_file": "testing/simulate_testing.R", "source_location": null, "weight": 1.0}, {"source": "simulate_testing_script", "target": "simulation_export_summaries", "relation": "calls", "confidence": "EXTRACTED", "confidence_score": 1.0, "source_file": "testing/simulate_testing.R", "source_location": null, "weight": 1.0}, {"source": "simulate_testing_script", "target": "simulation_export_tables", "relation": "calls", "confidence": "EXTRACTED", "confidence_score": 1.0, "source_file": "testing/simulate_testing.R", "source_location": null, "weight": 1.0}, {"source": "simulate_testing_script", "target": "scenario_sc1_bmi20pct_af_mrtl", "relation": "defines", "confidence": "EXTRACTED", "confidence_score": 1.0, "source_file": "testing/simulate_testing.R", "source_location": null, "weight": 1.0}, {"source": "scenario_sc1_bmi20pct_af_mrtl", "target": "exposure_bmi_curr_xps", "relation": "applies_to", "confidence": "EXTRACTED", "confidence_score": 1.0, "source_file": "testing/simulate_testing.R", "source_location": null, "weight": 1.0}, {"source": "scenario_sc1_bmi20pct_af_mrtl", "target": "exposure_prb_af_mrtl", "relation": "applies_to", "confidence": "EXTRACTED", "confidence_score": 1.0, "source_file": "testing/simulate_testing.R", "source_location": null, "weight": 1.0}], "hyperedges": []}